{"assets/11.png":["assets/11.png"],"assets/12.png":["assets/12.png"],"assets/13.png":["assets/13.png"],"assets/14.png":["assets/14.png"],"assets/23.png":["assets/23.png"],"assets/Group%20332.png":["assets/Group%20332.png"],"assets/b2.png":["assets/b2.png"],"assets/b_image2.png":["assets/b_image2.png"],"assets/b_image_1.png":["assets/b_image_1.png"],"assets/burger1.png":["assets/burger1.png"],"assets/burger2.png":["assets/burger2.png"],"assets/icon.png":["assets/icon.png"],"assets/logo.png":["assets/logo.png"],"packages/cupertino_icons/assets/CupertinoIcons.ttf":["packages/cupertino_icons/assets/CupertinoIcons.ttf"]}